tracenexus/__init__.py
tracenexus/cli.py
tracenexus/providers/__init__.py
tracenexus/providers/langfuse.py
tracenexus/providers/langsmith.py
tracenexus/server/__init__.py
tracenexus/server/mcp_server.py
tracenexus-0.1.7.dist-info/LICENSE.md
tracenexus-0.1.7.dist-info/METADATA
tracenexus-0.1.7.dist-info/WHEEL
tracenexus-0.1.7.dist-info/entry_points.txt
tracenexus-0.1.7.dist-info/RECORD
