Metadata-Version: 2.3
Name: tracenexus
Version: 0.1.7
Summary: A platform-agnostic MCP server for LLM observability
Author: Rajesh Sharma
Author-email: sharrajesh@gmail.com
Requires-Python: >=3.11,<4.0
Classifier: Programming Language :: Python :: 3
Classifier: Programming Language :: Python :: 3.11
Classifier: Programming Language :: Python :: 3.12
Classifier: Programming Language :: Python :: 3.13
Requires-Dist: aiohttp (>=3.11.18,<4.0.0)
Requires-Dist: fastmcp (>=2.3.4,<3.0.0)
Requires-Dist: langchain-mcp-adapters (>=0.1.0,<0.2.0)
Requires-Dist: langfuse (>=2.60.5,<3.0.0)
Requires-Dist: langsmith (>=0.3.42,<0.4.0)
Requires-Dist: pydantic (>=2.11.4,<3.0.0)
Requires-Dist: python-dotenv (>=1.0.0,<2.0.0)
Requires-Dist: typing-extensions (>=4.13.2,<5.0.0)
